quax/__init__.py
quax/_apply.py
quax/_apply_superoperator.py
quax/_common_channels.py
quax/_compose.py
quax/_distance_metrics.py
quax/_power.py
quax/_promotion.py
quax/_quantum_objects.py
quax/_random.py
quax/_state.py
quax/_superoperator_transformations.py
quax/_tensor.py
quax/_validation.py
quax/ensembles.py
quax/gates.py
quax/states.py
rigetti_quax-0.2.2.dist-info/METADATA
rigetti_quax-0.2.2.dist-info/WHEEL
rigetti_quax-0.2.2.dist-info/licenses/LICENSE
rigetti_quax-0.2.2.dist-info/RECORD
