Metadata-Version: 2.4
Name: rigetti-quax
Version: 0.2.2
Summary: A high-performance library for quantum information science built on top of JAX
License-Expression: Apache-2.0
License-File: LICENSE
Author: Bram Evert
Author-email: bevert@rigetti.com
Requires-Python: >=3.12
Classifier: Programming Language :: Python :: 3
Classifier: Programming Language :: Python :: 3.12
Classifier: Programming Language :: Python :: 3.13
Classifier: Programming Language :: Python :: 3.14
Requires-Dist: jax (>=0.8.2)
Project-URL: Documentation, https://rigetti.gitlab.io/application_benchmarking/quax
